MANIFEST.in
README.md
requirements.txt
setup.py
metadown/__init__.py
metadown/downloader.py
metadown.egg-info/PKG-INFO
metadown.egg-info/SOURCES.txt
metadown.egg-info/dependency_links.txt
metadown.egg-info/requires.txt
metadown.egg-info/top_level.txt
metadown/collectors/__init__.py
metadown/collectors/geonetwork.py
metadown/collectors/insitu.py
metadown/collectors/thredds.py
metadown/utils/__init__.py
metadown/utils/etree.py
metadown/utils/utils.py
tests/__init__.py
tests/test_geonetwork.py
tests/test_thredds.py