Metadata-Version: 1.1
Name: metadown
Version: 0.5
Summary: A Python library for collecting Met/Ocean metadata from various services
Home-page: https://github.com/asascience-open/metadown
Author: Kyle Wilcox
Author-email: kwilcox@sasascience.com
License: GPLv3
Platform: UNKNOWN
Classifier: Development Status :: 3 - Alpha
Classifier: Intended Audience :: Developers
Classifier: Intended Audience :: Science/Research
Classifier: License :: OSI Approved :: GNU General Public License v3 (GPLv3)
Classifier: Operating System :: POSIX :: Linux
Classifier: Programming Language :: Python
Classifier: Topic :: Scientific/Engineering
